resout/__init__.py
resout/test.py
resout-0.0.5.dist-info/METADATA
resout-0.0.5.dist-info/WHEEL
resout-0.0.5.dist-info/top_level.txt
resout-0.0.5.dist-info/RECORD
